UnityForHanifor/__init__.py
UnityForHanifor/unity.py
unityforhanifor-0.1.0.dist-info/licenses/LICENSE
unityforhanifor-0.1.0.dist-info/METADATA
unityforhanifor-0.1.0.dist-info/WHEEL
unityforhanifor-0.1.0.dist-info/top_level.txt
unityforhanifor-0.1.0.dist-info/RECORD
