Metadata-Version: 2.4
Name: UnityForHanifor
Version: 0.1.0
Summary: UnityForHanifor is a library for Hanifi Ormancı's project.
Home-page: https://github.com/hanifor/DeneyapProje
Author: Hanifi Ormancı
Author-email: hanifiormanci@hotmail.com
Classifier: Programming Language :: Python :: 3
Classifier: License :: OSI Approved :: MIT License
Classifier: Operating System :: OS Independent
Requires-Python: >=3.9
License-File: LICENSE
Dynamic: author
Dynamic: author-email
Dynamic: classifier
Dynamic: description-content-type
Dynamic: home-page
Dynamic: license-file
Dynamic: requires-python
Dynamic: summary
